wfp/__init__.py
wfp/_name.py
wfp/_version.py
wfp/app.py
wfp/error.py
wfp/experiment.py
wfp/pipeline.py
wfp-1.4.0.dist-info/METADATA
wfp-1.4.0.dist-info/WHEEL
wfp-1.4.0.dist-info/entry_points.txt
wfp-1.4.0.dist-info/top_level.txt
wfp-1.4.0.dist-info/RECORD
