Metadata-Version: 2.1
Name: wfp
Version: 1.4.0
Summary: A proxy application for kubeflow pipeline
Home-page: http://www.yunanbao.com.cn
Author: wangab
Author-email: wangab@yunanbao.com.cn
License: UNKNOWN
Platform: UNKNOWN
Classifier: Programming Language :: Python :: 3
Classifier: License :: OSI Approved :: MIT License
Classifier: Operating System :: OS Independent
Requires-Python: >=3.5
Requires-Dist: traitlets (==4.3.2)
Requires-Dist: kfp (==0.1.11)
Requires-Dist: wf-pipeline-api (==1.2.0rc0)
